.gitignore
LICENSE
MANIFEST.in
README.md
build_package.sh
requirements.txt
setup.cfg
setup.py
bopfast.egg-info/PKG-INFO
bopfast.egg-info/SOURCES.txt
bopfast.egg-info/dependency_links.txt
bopfast.egg-info/entry_points.txt
bopfast.egg-info/requires.txt
bopfast.egg-info/top_level.txt
bopscrk/__main__.py
bopscrk/bopscrk.cfg
bopscrk/bopscrk.py
bopscrk/modules/__init__.py
bopscrk/modules/args.py
bopscrk/modules/auxiliars.py
bopscrk/modules/banners.py
bopscrk/modules/color.py
bopscrk/modules/combinators.py
bopscrk/modules/config.py
bopscrk/modules/excluders.py
bopscrk/modules/main.py
bopscrk/modules/transforms.py