Metadata-Version: 2.4
Name: bopfast
Version: 0.1.1
Summary: Faster bopscrk, Generate smart and powerful wordlists
License: GNU General Public License v3.0
License-File: LICENSE
Requires-Dist: requests
Requires-Dist: alive-progress
Dynamic: description
Dynamic: description-content-type
Dynamic: license
Dynamic: license-file
Dynamic: requires-dist
Dynamic: summary
